ivy_vision/__init__.py
ivy_vision/containers.py
ivy_vision/implicit.py
ivy_vision/mesh.py
ivy_vision/optical_flow.py
ivy_vision/padding.py
ivy_vision/projective_geometry.py
ivy_vision/quantization.py
ivy_vision/sdf.py
ivy_vision/single_view_geometry.py
ivy_vision/smoothing.py
ivy_vision/two_view_geometry.py
ivy_vision/voxel_grids.py
ivy_vision-1.1.9.dist-info/LICENSE
ivy_vision-1.1.9.dist-info/METADATA
ivy_vision-1.1.9.dist-info/WHEEL
ivy_vision-1.1.9.dist-info/top_level.txt
ivy_vision-1.1.9.dist-info/RECORD
